allauth_id4me/__init__.py
allauth_id4me/admin.py
allauth_id4me/forms.py
allauth_id4me/models.py
allauth_id4me/provider.py
allauth_id4me/tests.py
allauth_id4me/urls.py
allauth_id4me/utils.py
allauth_id4me/views.py
allauth_id4me/migrations/0001_initial.py
allauth_id4me/migrations/__init__.py
allauth_id4me/templates/id4me/base.html
allauth_id4me/templates/id4me/login.html
django_allauth_id4me-0.0.13.dist-info/LICENSE
django_allauth_id4me-0.0.13.dist-info/METADATA
django_allauth_id4me-0.0.13.dist-info/WHEEL
django_allauth_id4me-0.0.13.dist-info/top_level.txt
django_allauth_id4me-0.0.13.dist-info/RECORD
