Metadata-Version: 2.1
Name: django-allauth-id4me
Version: 0.0.13
Summary: Social provider for django-allauth - ID4me https://id4me.org
Home-page: https://gitlab.com/ID4me/django-allauth-id4me
Author: Pawel Kowalik
Author-email: pawel-kow@users.noreply.github.com
License: https://gitlab.com/ID4me/django-allauth-id4me/blob/master/LICENSE
Platform: UNKNOWN
Classifier: Development Status :: 3 - Alpha
Classifier: Intended Audience :: Developers
Classifier: Topic :: Software Development :: Libraries :: Python Modules
Classifier: Environment :: Web Environment
Classifier: Topic :: Internet
Classifier: License :: OSI Approved :: GNU General Public License v3 (GPLv3)
Classifier: Operating System :: OS Independent
Classifier: Programming Language :: Python
Classifier: Programming Language :: Python :: 3.6
Classifier: Programming Language :: Python :: 3.7
Classifier: Framework :: Django
Classifier: Framework :: Django :: 1.11
Classifier: Framework :: Django :: 2.0
Classifier: Framework :: Django :: 2.1
Requires-Dist: id4me-rp-client (>=0.0.23)
Requires-Dist: Django (>=1.11.16)
Requires-Dist: django-allauth (>=0.38.0)
